{
    "name": "<YOUR NAME>",
    "netlify_subdomain": "<YOUR NETLIFY URL>",
    "optional_dns": "<YOUR CUSTOM DOMAIN NAME IF YOU HAVE ONE OR PLAN TO USE ONE>"
    "blog_post_1": {
        "title": "<TITLE1>",
        "url": "<MEDIUM OR WEB URL>",
        "keywords": ["<KWD1>","<KWD2>","<KWD3>"]
    },
    "blog_post_2": {
        "title": "<TITLE2>",
        "url": "<MEDIUM OR WEB URL>",
        "keywords": ["<KWD1>","<KWD2>","<KWD3>"]
    },
    "blog_post_3": {
        "title": "<TITLE3>",
        "url": "<MEDIUM OR WEB URL>",
        "keywords": ["<KWD1>","<KWD2>","<KWD3>"]
    },
    "my_linkedin": "<URL TO LINKEDIN>",
    "latex": "<YOUR LATEX (REMEMBER VALID JSON)>"
}
